catnet/__init__.py
catnet/catnet.py
catnet/data/__init__.py
catnet/data/attributes.csv
catnet/data/long.csv
catnet/data/same_cell.csv
catnet-0.1.0.dist-info/LICENSE
catnet-0.1.0.dist-info/METADATA
catnet-0.1.0.dist-info/WHEEL
catnet-0.1.0.dist-info/RECORD
