Metadata-Version: 2.1
Name: catnet
Version: 0.1.0
Summary: Create networks of categories from literature review and other tables
Home-page: https://github.com/CamiBetancur/catnet
License: GNU GPLv3
Keywords: networks,literature review,categorical data
Author: Juan Camilo Betancur Jaramillo
Author-email: juan.betancur@sei.org
Maintainer: Juan Camilo Betancur Jaramillo
Maintainer-email: juan.betancur@sei.org
Requires-Python: >=3.12,<4.0
Classifier: License :: OSI Approved :: GNU General Public License v3 (GPLv3)
Classifier: License :: Other/Proprietary License
Classifier: Operating System :: OS Independent
Classifier: Programming Language :: Python :: 3
Classifier: Programming Language :: Python :: 3.12
Classifier: Programming Language :: Python :: 3.13
Classifier: Topic :: Scientific/Engineering
Classifier: Topic :: Text Processing
Requires-Dist: importlib (>=1.0.4,<2.0.0)
Requires-Dist: pandas (>=2.2.3,<3.0.0)
Requires-Dist: pathlib (>=1.0.1,<2.0.0)
Project-URL: Repository, https://github.com/CamiBetancur/catnet
